{
  "id": "phoenix_plume",
  "grade": 0,
  "image": "./images/items/phoenix_plume.png",
  "name": "Phoenix Plume",
  "type": "Expedition Currency",
  "bound": "Binds when obtained",
  "destruction": "<span style=\"color: #C24B46\">Unsellable</span>, <span style=\"color: #C24B46\">Indestructible</span>, <span style=\"color: #C24B46\">Cannot be dismantled</span>",
  "description": "A magical feather that brings the dead back to life.<br><span style=\"color: #FFFFAC\">Right-click on the item to move it to the Expedition Currency Inventory.</span>"
}